daylio_to_md/__init__.py
daylio_to_md/__main__.py
daylio_to_md/config.py
daylio_to_md/dated_entries_group.py
daylio_to_md/dated_entry.py
daylio_to_md/errors.py
daylio_to_md/librarian.py
daylio_to_md/utils.py
daylio_to_md/entry/mood.py
daylio_obsidian_parser-0.2.dist-info/LICENSE
daylio_obsidian_parser-0.2.dist-info/METADATA
daylio_obsidian_parser-0.2.dist-info/WHEEL
daylio_obsidian_parser-0.2.dist-info/entry_points.txt
daylio_obsidian_parser-0.2.dist-info/top_level.txt
daylio_obsidian_parser-0.2.dist-info/RECORD
