Metadata-Version: 2.1
Name: daylio-obsidian-parser
Version: 0.2
Summary: Converts Daylio app .csv file into markdown files for use in Obsidian.
Author-email: Paweł Ilnicki <59067099+DeutscheGabanna@users.noreply.github.com>
License: GNU GENERAL PUBLIC LICENSE
Keywords: csv,markdown,.md,.csv,daylio,obsidian,file converter
Classifier: Topic :: Text Processing :: Markup :: Markdown
Classifier: Intended Audience :: Developers
Classifier: Intended Audience :: End Users/Desktop
Classifier: Topic :: Utilities
Classifier: Development Status :: 3 - Alpha
Classifier: Operating System :: OS Independent
Classifier: Programming Language :: Python :: 3
Requires-Python: >=3.8
License-File: LICENSE
